optitime/__init__.py
optitime/diagnostics.py
optitime/exceptions.py
optitime/explainability.py
optitime/model.py
optitime/utils.py
optitime/datasets/__init__.py
optitime/datasets/air_passengers.csv
optitime/datasets/airlines_traffic.csv
optitime/datasets/shampoo_sales.csv
optitime/datasets/us_acc_deaths.csv
optitime_prophet-0.2.3.dist-info/METADATA
optitime_prophet-0.2.3.dist-info/WHEEL
optitime_prophet-0.2.3.dist-info/top_level.txt
optitime_prophet-0.2.3.dist-info/RECORD
