Metadata-Version: 2.4
Name: optitime-prophet
Version: 0.2.3
Summary: A Prophet-inspired forecasting library distilling OptiWisdom OptiScorer insights into autoregressive, changepoint, and diagnostic enhancements.
Author-email: Şadi Evren Şeker <optitime@optiwisdom.com>
License: MIT
Project-URL: Homepage, https://github.com/bilgisayarkavramlari/optitime
Project-URL: Documentation, https://github.com/bilgisayarkavramlari/optitime
Project-URL: Issues, https://github.com/bilgisayarkavramlari/optitime/issues
Keywords: forecasting,prophet,time-series,autoregressive,python
Classifier: Development Status :: 4 - Beta
Classifier: Programming Language :: Python :: 3
Classifier: Intended Audience :: Science/Research
Classifier: Topic :: Scientific/Engineering :: Information Analysis
Requires-Python: >=3.9
Requires-Dist: numpy>=1.23
Requires-Dist: pandas>=1.5
Provides-Extra: visuals
Requires-Dist: matplotlib>=3.6; extra == "visuals"
